gravitino/__init__.py
gravitino/constants.py
gravitino/exceptions.py
gravitino/gravitino_client.py
gravitino/name_identifier.py
gravitino/namespace.py
gravitino/service.py
gravitino/typing.py
gravitino-0.5.0.dist-info/METADATA
gravitino-0.5.0.dist-info/WHEEL
gravitino-0.5.0.dist-info/top_level.txt
gravitino-0.5.0.dist-info/RECORD
