Metadata-Version: 2.1
Name: gravitino
Version: 0.5.0
Summary: Python lib/client for Gravitino
Home-page: https://github.com/datastrato/gravitino
Author: datastrato
Requires-Python: >=3.8
Requires-Dist: setuptools
Requires-Dist: twine
Requires-Dist: wheel
Provides-Extra: dev
Requires-Dist: requests ; extra == 'dev'
Requires-Dist: dataclasses-json ; extra == 'dev'
